django_solvitize/__init__.py
django_solvitize/readme.md
django_solvitize/ErrorApp/__init__.py
django_solvitize/ErrorApp/admin.py
django_solvitize/ErrorApp/apps.py
django_solvitize/ErrorApp/models.py
django_solvitize/ErrorApp/serializers.py
django_solvitize/ErrorApp/tests.py
django_solvitize/ErrorApp/urls.py
django_solvitize/ErrorApp/views.py
django_solvitize/ErrorApp/migrations/0001_initial.py
django_solvitize/ErrorApp/migrations/__init__.py
django_solvitize/core/__init__.py
django_solvitize/core/admin.py
django_solvitize/core/apps.py
django_solvitize/core/models.py
django_solvitize/core/tests.py
django_solvitize/core/views.py
django_solvitize/core/migrations/__init__.py
django_solvitize/firebase/__init__.py
django_solvitize/firebase/admin.py
django_solvitize/firebase/apps.py
django_solvitize/firebase/models.py
django_solvitize/firebase/readme.md
django_solvitize/firebase/serializers.py
django_solvitize/firebase/tests.py
django_solvitize/firebase/urls.py
django_solvitize/firebase/views.py
django_solvitize/firebase/auth/__init__.py
django_solvitize/firebase/auth/verify.py
django_solvitize/firebase/migrations/0001_initial.py
django_solvitize/firebase/migrations/__init__.py
django_solvitize/firebase/notifications/__init__.py
django_solvitize/firebase/notifications/notifications.py
django_solvitize/utils/DynamicFieldsModel.py
django_solvitize/utils/GlobalFunctions.py
django_solvitize/utils/GlobalImports.py
django_solvitize/utils/__init__.py
django_solvitize/utils/constants.py
django_solvitize/utils/custompagination.py
django_solvitize/utils/otp_handler.py
django_solvitize-0.0.6.dist-info/licenses/LICENSE
django_solvitize-0.0.6.dist-info/METADATA
django_solvitize-0.0.6.dist-info/WHEEL
django_solvitize-0.0.6.dist-info/top_level.txt
django_solvitize-0.0.6.dist-info/RECORD
