Metadata-Version: 2.4
Name: django_solvitize
Version: 0.0.6
Summary: A reusable Django package with apps and utilities
Home-page: https://github.com/JasirMJ/django_solvitize
Author: Mohamed Jasir K P
Author-email: jasirmj@gmail.com
Classifier: Programming Language :: Python :: 3
Classifier: Framework :: Django
Classifier: License :: OSI Approved :: MIT License
Classifier: Operating System :: OS Independent
License-File: LICENSE
Requires-Dist: Django>=3.2
Dynamic: author
Dynamic: author-email
Dynamic: classifier
Dynamic: home-page
Dynamic: license-file
Dynamic: requires-dist
Dynamic: summary
